<PAMDataset>
  <Metadata>
    <MDI key="DataType">Generic</MDI>
  </Metadata>
  <Metadata domain="Esri">
    <MDI key="PyramidResamplingType">NEAREST</MDI>
  </Metadata>
  <PAMRasterBand band="1">
    <Histograms>
      <HistItem>
        <HistMin>0.5266667008399963</HistMin>
        <HistMax>64.22000122070313</HistMax>
        <BucketCount>256</BucketCount>
        <IncludeOutOfRange>1</IncludeOutOfRange>
        <Approximate>0</Approximate>
        <HistCounts>3155|4740|1916|1580|1346|1252|961|681|654|407|337|278|214|208|135|126|139|151|179|246|294|285|293|228|251|284|311|318|392|509|467|477|461|556|488|686|576|541|472|403|365|429|367|488|530|531|546|590|449|425|386|337|335|281|303|270|293|259|310|293|327|401|332|436|537|653|591|671|570|556|556|681|706|639|553|606|732|732|684|740|799|883|929|910|948|965|913|968|924|829|812|733|583|521|513|453|422|449|519|541|429|423|378|391|357|307|385|338|282|358|430|335|315|282|287|202|171|142|171|142|155|131|148|175|150|138|147|112|93|97|72|111|127|165|180|220|285|322|309|345|339|363|372|382|364|419|474|557|416|353|370|363|345|381|337|332|309|356|306|265|254|242|234|176|173|151|147|136|173|206|205|190|211|201|202|222|248|234|210|206|179|231|257|236|224|210|279|240|224|249|261|321|318|270|200|185|232|338|251|238|222|177|204|214|148|245|233|224|221|301|274|316|871|1430|1269|1336|1818|2194|887|432|337|207|195|393|309|118|28|7|2|3|0|0|3|1|1|1|2|0|1|0|1|0|2|2|2|3|2|4|0|0|0|1|0|2|1|1</HistCounts>
      </HistItem>
    </Histograms>
    <Metadata>
      <MDI key="RepresentationType">ATHEMATIC</MDI>
      <MDI key="STATISTICS_COVARIANCES">318.695055921755</MDI>
      <MDI key="STATISTICS_MAXIMUM">64.220001220703</MDI>
      <MDI key="STATISTICS_MEAN">24.718305971087</MDI>
      <MDI key="STATISTICS_MINIMUM">0.52666670084</MDI>
      <MDI key="STATISTICS_SKIPFACTORX">1</MDI>
      <MDI key="STATISTICS_SKIPFACTORY">1</MDI>
      <MDI key="STATISTICS_STDDEV">17.852032263072</MDI>
    </Metadata>
  </PAMRasterBand>
</PAMDataset>
