<PAMDataset>
  <Metadata>
    <MDI key="DataType">Generic</MDI>
  </Metadata>
  <Metadata domain="Esri">
    <MDI key="PyramidResamplingType">NEAREST</MDI>
  </Metadata>
  <PAMRasterBand band="1">
    <Histograms>
      <HistItem>
        <HistMin>15.32666683197021</HistMin>
        <HistMax>23.45666694641113</HistMax>
        <BucketCount>256</BucketCount>
        <IncludeOutOfRange>1</IncludeOutOfRange>
        <Approximate>0</Approximate>
        <HistCounts>4|2|2|2|1|4|1|3|1|0|0|3|3|1|5|9|3|3|9|3|12|8|11|20|14|8|19|16|18|31|33|36|19|27|22|35|31|45|54|41|47|53|46|54|67|59|64|89|84|100|106|136|107|100|124|113|128|130|111|148|163|183|148|168|137|151|145|181|177|182|171|161|185|135|176|170|165|193|162|185|176|166|191|202|194|196|167|187|224|203|206|192|265|266|201|258|233|277|270|283|298|291|315|313|338|281|336|305|324|356|286|329|352|354|332|366|366|335|374|333|366|408|367|392|343|390|401|478|443|546|460|520|532|499|606|555|576|498|574|622|589|560|530|669|666|722|751|694|746|740|849|764|1136|970|1139|1042|999|1200|1144|1313|1036|1216|1399|1458|1627|1370|1379|1306|1526|1296|1193|1076|893|1000|869|1004|979|1171|1393|1459|1287|939|978|840|875|847|683|790|699|743|681|768|690|741|692|616|632|569|731|611|697|675|639|700|654|757|636|752|727|629|734|569|630|473|483|515|480|471|399|410|369|421|407|409|453|398|471|415|400|336|311|291|239|230|193|184|151|193|133|151|156|103|98|85|97|68|74|60|65|47|33|42|42|23|20|2</HistCounts>
      </HistItem>
    </Histograms>
    <Metadata>
      <MDI key="RepresentationType">ATHEMATIC</MDI>
      <MDI key="STATISTICS_COVARIANCES">1.85970285794395</MDI>
      <MDI key="STATISTICS_MAXIMUM">23.456666946411</MDI>
      <MDI key="STATISTICS_MEAN">20.475579136396</MDI>
      <MDI key="STATISTICS_MINIMUM">15.32666683197</MDI>
      <MDI key="STATISTICS_SKIPFACTORX">1</MDI>
      <MDI key="STATISTICS_SKIPFACTORY">1</MDI>
      <MDI key="STATISTICS_STDDEV">1.3637092277843</MDI>
    </Metadata>
  </PAMRasterBand>
</PAMDataset>
