<PAMDataset>
  <Metadata>
    <MDI key="DataType">Generic</MDI>
  </Metadata>
  <Metadata domain="Esri">
    <MDI key="PyramidResamplingType">NEAREST</MDI>
  </Metadata>
  <PAMRasterBand band="1">
    <Histograms>
      <HistItem>
        <HistMin>44.40777969360352</HistMin>
        <HistMax>82.17082977294922</HistMax>
        <BucketCount>256</BucketCount>
        <IncludeOutOfRange>1</IncludeOutOfRange>
        <Approximate>0</Approximate>
        <HistCounts>1|0|0|1|0|1|0|0|0|0|0|0|0|1|0|0|0|1|0|0|1|1|2|0|1|0|2|3|4|3|1|9|13|12|11|16|20|23|31|36|47|50|52|50|67|78|82|103|97|121|136|149|205|193|229|218|223|242|263|262|260|265|261|284|279|277|275|253|274|249|264|231|259|226|258|224|230|238|236|233|242|253|231|222|247|231|251|255|236|248|253|276|280|298|304|317|348|352|372|386|347|329|421|425|399|400|429|362|380|384|382|306|250|232|201|202|185|160|172|178|138|153|170|177|179|169|170|165|160|180|134|146|119|110|109|92|82|77|84|71|61|67|62|64|50|55|63|63|42|46|66|62|68|67|46|48|44|51|57|43|36|48|46|54|48|38|43|42|42|53|44|46|39|43|40|41|40|47|42|37|41|42|50|26|34|33|39|29|36|27|23|32|37|19|33|28|25|26|20|25|18|20|20|20|17|25|16|18|11|15|18|20|16|14|9|15|12|18|16|17|10|16|12|14|5|8|15|7|14|9|6|7|5|7|2|5|5|3|1|4|5|3|1|2|0|0|0|0|0|0|0|0|0|0|0|1</HistCounts>
      </HistItem>
    </Histograms>
    <Metadata>
      <MDI key="RepresentationType">ATHEMATIC</MDI>
      <MDI key="STATISTICS_COVARIANCES">29.40051526448223</MDI>
      <MDI key="STATISTICS_MAXIMUM">82.170829772949</MDI>
      <MDI key="STATISTICS_MEAN">59.256764725214</MDI>
      <MDI key="STATISTICS_MINIMUM">44.407779693604</MDI>
      <MDI key="STATISTICS_SKIPFACTORX">1</MDI>
      <MDI key="STATISTICS_SKIPFACTORY">1</MDI>
      <MDI key="STATISTICS_STDDEV">5.4222241990241</MDI>
    </Metadata>
  </PAMRasterBand>
</PAMDataset>
